async_chain/__init__.py
async_chain/chain.py
async_chain/decorators.py
async_chain/tests/test_integration.py
async_chain-0.1.3.dist-info/LICENSE.txt
async_chain-0.1.3.dist-info/METADATA
async_chain-0.1.3.dist-info/WHEEL
async_chain-0.1.3.dist-info/RECORD
