Metadata-Version: 2.3
Name: async-chain
Version: 0.1.3
Summary: A coroutine builder
License: LGPL-3.0-or-later
Keywords: asyncio
Author: Stefano Pigozzi
Author-email: me@steffo.eu
Requires-Python: >=3.6,<4.0
Classifier: Development Status :: 3 - Alpha
Classifier: Framework :: AsyncIO
Classifier: Intended Audience :: Developers
Classifier: License :: OSI Approved :: GNU Lesser General Public License v3 or later (LGPLv3+)
Classifier: Operating System :: OS Independent
Classifier: Programming Language :: Python :: 3
Classifier: Programming Language :: Python :: 3.6
Classifier: Programming Language :: Python :: 3.7
Classifier: Programming Language :: Python :: 3.8
Classifier: Programming Language :: Python :: 3.9
Classifier: Programming Language :: Python :: 3.10
Classifier: Programming Language :: Python :: 3.11
Classifier: Programming Language :: Python :: 3.12
Classifier: Programming Language :: Python :: 3.13
Project-URL: Documentation, https://forge.steffo.eu/steffo/async-chain/src/branch/main/README.md
Project-URL: Repository, https://forge.steffo.eu/steffo/async-chain
